PyQQSkeyTool/__init__.py
PyQQSkeyTool/_core.py
PyQQSkeyTool/api.py
PyQQSkeyTool/constant.py
PyQQSkeyTool/client/__init__.py
PyQQSkeyTool/client/qun.py
PyQQSkeyTool/client/qzone.py
PyQQSkeyTool/tool/__init__.py
PyQQSkeyTool/tool/accounts_info.py
PyQQSkeyTool/tool/clientkey.py
client/__init__.py
client/qun.py
client/qzone.py
PyQQSkeyTool-1.0.5.dist-info/LICENSE
PyQQSkeyTool-1.0.5.dist-info/METADATA
PyQQSkeyTool-1.0.5.dist-info/WHEEL
PyQQSkeyTool-1.0.5.dist-info/top_level.txt
PyQQSkeyTool-1.0.5.dist-info/RECORD
